loco_hd-0.2.0.dist-info/METADATA
loco_hd-0.2.0.dist-info/WHEEL
loco_hd-0.2.0.dist-info/licenses/LICENSE
loco_hd/__init__.py
loco_hd/__main__.py
loco_hd/atom_converter_utils.py
loco_hd/loco_hd.cpython-312-x86_64-linux-gnu.so
loco_hd/loco_hd.pyi
loco_hd/py.typed
loco_hd-0.2.0.dist-info/RECORD
