Metadata-Version: 2.4
Name: loco_hd
Version: 0.2.0
Classifier: Programming Language :: Rust
Classifier: Programming Language :: Python :: Implementation :: CPython
Classifier: Programming Language :: Python :: Implementation :: PyPy
Requires-Dist: biopython>=1.80
Requires-Dist: numpy>=1.21.6
License-File: LICENSE
Summary: Implementation of the LoCoHD metric for quantitative protein structure and substructure comparison
Author-email: Zsolt Fazekas <zsolt.fazekas.9@gmail.com>
Requires-Python: >=3.12
